{
  "totalJPY": 103528,
  "assets": [
    {
      "currency": "JPY",
      "amount": 36991,
      "available": 36991,
      "jpyValue": 36991
    },
    {
      "currency": "BTC",
      "amount": 0.0049945,
      "available": 0.0049945,
      "jpyValue": 51328
    },
    {
      "currency": "ETH",
      "amount": 0.0502996,
      "available": 0.0502996,
      "jpyValue": 15209
    },
    {
      "currency": "SHIB",
      "amount": 3021695.7756693,
      "available": 3021695.7756693,
      "jpyValue": 0
    },
    {
      "currency": "XYM",
      "amount": 504.032258,
      "available": 504.032258,
      "jpyValue": 0
    }
  ],
  "prices": {
    "BTC": 10276974,
    "ETH": 302363,
    "XRP": 212.59
  },
  "fetchedAt": "2026-02-27T18:00:04.836Z"
}