{
  "totalJPY": 104825,
  "assets": [
    {
      "currency": "JPY",
      "amount": 44256,
      "available": 44256,
      "jpyValue": 44256
    },
    {
      "currency": "BTC",
      "amount": 0.0049945,
      "available": 0.0049945,
      "jpyValue": 52833
    },
    {
      "currency": "ETH",
      "amount": 0.024876,
      "available": 0.024876,
      "jpyValue": 7737
    },
    {
      "currency": "SHIB",
      "amount": 3021695.7756693,
      "available": 3021695.7756693,
      "jpyValue": 0
    },
    {
      "currency": "XYM",
      "amount": 504.032258,
      "available": 504.032258,
      "jpyValue": 0
    }
  ],
  "prices": {
    "BTC": 10578145,
    "ETH": 311013,
    "XRP": 216.87
  },
  "fetchedAt": "2026-02-10T15:00:05.689Z"
}