{
  "totalJPY": 106707,
  "assets": [
    {
      "currency": "JPY",
      "amount": 53300,
      "available": 53300,
      "jpyValue": 53300
    },
    {
      "currency": "BTC",
      "amount": 0.0049945,
      "available": 0.0049945,
      "jpyValue": 53225
    },
    {
      "currency": "ETH",
      "amount": 0.0005896,
      "available": 0.0005896,
      "jpyValue": 182
    },
    {
      "currency": "SHIB",
      "amount": 3021695.7756693,
      "available": 3021695.7756693,
      "jpyValue": 0
    },
    {
      "currency": "XYM",
      "amount": 504.032258,
      "available": 504.032258,
      "jpyValue": 0
    }
  ],
  "prices": {
    "BTC": 10656803,
    "ETH": 308729,
    "XRP": 225.16
  },
  "fetchedAt": "2026-02-21T16:00:05.778Z"
}