{
  "totalJPY": 103807,
  "assets": [
    {
      "currency": "JPY",
      "amount": 49068,
      "available": 49068,
      "jpyValue": 49068
    },
    {
      "currency": "BTC",
      "amount": 0.0049945,
      "available": 0.0049945,
      "jpyValue": 51612
    },
    {
      "currency": "ETH",
      "amount": 0.0101396,
      "available": 0.0101396,
      "jpyValue": 3127
    },
    {
      "currency": "SHIB",
      "amount": 3021695.7756693,
      "available": 3021695.7756693,
      "jpyValue": 0
    },
    {
      "currency": "XYM",
      "amount": 504.032258,
      "available": 504.032258,
      "jpyValue": 0
    }
  ],
  "prices": {
    "BTC": 10333680,
    "ETH": 308438,
    "XRP": 214.13
  },
  "fetchedAt": "2026-03-01T17:00:11.384Z"
}