{
  "totalJPY": 108551,
  "assets": [
    {
      "currency": "JPY",
      "amount": 615,
      "available": 615,
      "jpyValue": 615
    },
    {
      "currency": "BTC",
      "amount": 0.00830973,
      "available": 0.00830973,
      "jpyValue": 89781
    },
    {
      "currency": "ETH",
      "amount": 0.057115,
      "available": 0.057115,
      "jpyValue": 18155
    },
    {
      "currency": "SHIB",
      "amount": 3021695.7756693,
      "available": 3021695.7756693,
      "jpyValue": 0
    },
    {
      "currency": "XYM",
      "amount": 504.032258,
      "available": 504.032258,
      "jpyValue": 0
    }
  ],
  "prices": {
    "BTC": 10804364,
    "ETH": 317869,
    "XRP": 220.37
  },
  "fetchedAt": "2026-02-07T15:00:04.382Z"
}